otp/__init__.py
otp/cli.py
otp/configure.py
otp/core.py
otp/otp.py
otp/progress.py
otp/qr_code.py
otp/token.py
otp_gen-0.1.2.data/scripts/otp
otp_gen-0.1.2.dist-info/DESCRIPTION.rst
otp_gen-0.1.2.dist-info/METADATA
otp_gen-0.1.2.dist-info/RECORD
otp_gen-0.1.2.dist-info/WHEEL
otp_gen-0.1.2.dist-info/metadata.json
otp_gen-0.1.2.dist-info/top_level.txt
