Metadata-Version: 2.0
Name: otp-gen
Version: 0.1.2
Summary: Generate one time passwords
Home-page: http://github.com/karakays/otp-py/
Author: Selçuk Karakayalı
Author-email: skarakayali@gmail.com
License: MIT
Keywords: otp,otp-codes,otp-generator,authenticator
Platform: UNKNOWN
Requires-Python: >=3
Requires-Dist: pyqrcode (>=1.2.1)
